{"started_on": {"$dt": "2022-05-08T11:28:04.307061"}, "duration": 62, "sample_id": 2, "owner": null, "id": 2, "category": "file", "priority": 2, "guest": {"status": "stopped", "name": "192.168.56.101", "label": "192.168.56.101", "manager": "VirtualBox", "started_on": "2022-05-08 11:28:04", "shutdown_on": "2022-05-08 11:29:06"}, "clock": {"$dt": "2022-05-08T11:28:03.921393"}, "custom": null, "machine": "192.168.56.101", "platform": null, "memory": false, "status": "completed", "tags": [], "processing": null, "enforce_timeout": false, "completed_on": {"$dt": "2022-05-08T11:29:06.492956"}, "target": "/tmp/cuckoo-tmp-cuckoo/tmpNaCVbZ/istockphoto-1188445864-612x612.jpg", "package": "", "route": "none", "timeout": 120, "submit_id": 2, "options": {"procmemdump": "yes", "route": "none"}, "added_on": {"$dt": "2022-05-08T11:28:03.921407"}}