{"started_on": {"$dt": "2022-05-13T01:37:25.263846"}, "duration": 86, "sample_id": 2, "owner": null, "id": 33, "category": "file", "priority": 2, "guest": {"status": "stopped", "name": "192.168.56.102", "label": "192.168.56.102", "manager": "VirtualBox", "started_on": "2022-05-13 01:37:25", "shutdown_on": "2022-05-13 01:38:51"}, "clock": {"$dt": "2022-05-13T01:37:24.584767"}, "custom": null, "machine": "192.168.56.102", "platform": null, "memory": false, "status": "completed", "tags": [], "processing": null, "enforce_timeout": false, "completed_on": {"$dt": "2022-05-13T01:38:51.816524"}, "target": "/tmp/cuckoo-tmp-cuckoo/tmp8uf9RQ/istockphoto-1188445864-612x612.jpg", "package": "", "route": "none", "timeout": 120, "submit_id": 33, "options": {"procmemdump": "yes", "route": "none"}, "added_on": {"$dt": "2022-05-13T01:37:24.584784"}}